pygeofilter_duckdb/__about__.py
pygeofilter_duckdb/__init__.py
pygeofilter_duckdb/evaluate.py
pygeofilter_duckdb-0.1.0.dist-info/METADATA
pygeofilter_duckdb-0.1.0.dist-info/WHEEL
pygeofilter_duckdb-0.1.0.dist-info/licenses/LICENSE
pygeofilter_duckdb-0.1.0.dist-info/RECORD
