Metadata-Version: 2.4
Name: pygeofilter-duckdb
Version: 0.1.0
Project-URL: Documentation, https://github.com/Terradue/pygeofilter-duckdb#readme
Project-URL: Issues, https://github.com/Terradue/pygeofilter-duckdb/issues
Project-URL: Source, https://github.com/Terradue/pygeofilter-duckdb
Author-email: Fabrice Brito <fabrice.brito@terradue.com>, Simone Tripodi <simone.tripodi@terradue.com>
License-Expression: MIT
License-File: LICENSE
Classifier: Development Status :: 4 - Beta
Classifier: Programming Language :: Python
Classifier: Programming Language :: Python :: 3.8
Classifier: Programming Language :: Python :: 3.9
Classifier: Programming Language :: Python :: 3.10
Classifier: Programming Language :: Python :: 3.11
Classifier: Programming Language :: Python :: 3.12
Classifier: Programming Language :: Python :: Implementation :: CPython
Classifier: Programming Language :: Python :: Implementation :: PyPy
Requires-Python: >=3.8
Requires-Dist: duckdb<1.2.0
Requires-Dist: duckdb>=0.2.0
Requires-Dist: pygeofilter>=0.2.4
Requires-Dist: pystac-client
Requires-Dist: pytest
Requires-Dist: shapely
Requires-Dist: stac-geoparquet
